cos/__init__.py
cos/cos.py
backwork_upload_cos-0.3.2.dist-info/LICENSE
backwork_upload_cos-0.3.2.dist-info/METADATA
backwork_upload_cos-0.3.2.dist-info/WHEEL
backwork_upload_cos-0.3.2.dist-info/entry_points.txt
backwork_upload_cos-0.3.2.dist-info/top_level.txt
backwork_upload_cos-0.3.2.dist-info/RECORD
