Metadata-Version: 2.1
Name: backwork-upload-cos
Version: 0.3.2
Summary: Backwork plug-in for IBM Cloud Object Storage uploads.
Home-page: https://github.com/IBM/backwork-upload-cos
Author: Michael Lin
Author-email: michael.lin1@ibm.com
License: Apache 2
Classifier: Development Status :: 3 - Alpha
Classifier: Environment :: Console
Classifier: Intended Audience :: Developers
Classifier: Intended Audience :: System Administrators
Classifier: Operating System :: POSIX :: Linux
Classifier: License :: OSI Approved :: Apache Software License
Classifier: Topic :: Database
Classifier: Topic :: System :: Archiving :: Backup
Classifier: Topic :: Utilities
License-File: LICENSE
Requires-Dist: backwork
Requires-Dist: ibm-cos-sdk (>=2.4.4)
